aocast/__init__.py
aocast/aocast.py
aocast/simpleTest.py
aocast/test.py
aocast-0.1.dist-info/METADATA
aocast-0.1.dist-info/RECORD
aocast-0.1.dist-info/WHEEL
aocast-0.1.dist-info/top_level.txt
