Metadata-Version: 2.1
Name: aocast
Version: 0.1
Summary: ADAPTATIVE OPERATOR FORECAST
Home-page: https://github.com/felipeardilac/aocast
Author: Felipe Ardila Camelo
Author-email: felipeardilac@gmail.com
License: MIT
Platform: UNKNOWN
